{"arkId":"cl010027259","url":"https:\/\/collections.louvre.fr\/ark:\/53355\/cl010027259","modified ":"2026-02-15","title":"scarabo\u00efde","titleComplement":"","denominationTitle":[{"type":"D\u00e9nomination","value":"scarabo\u00efde"}],"displayDateCreated":"Date de cr\u00e9ation\/fabrication : Nouvel Empire (-1550 - -1069)","currentLocation":"non expos\u00e9","room":"","isMuseesNationauxRecuperation":false,"dateCreated":[{"startYear":-1550,"endYear":-1069,"imprecision":"","text":"Nouvel Empire","type":"Date de cr\u00e9ation\/fabrication","doubt":""}],"creator":[],"objectNumber":[{"value":"AF 11490","type":"Num\u00e9ro principal"}],"collection":"D\u00e9partement des Antiquit\u00e9s \u00e9gyptiennes","printsDrawingsEntity":"","printsDrawingsCollection":"","objectType":"","originalObject":"","printState":"","description":"singe (accroupi, mangeant) ; perc\u00e9 dans la longueur\r\n\r\nD\u00e9cor : hi\u00e9roglyphes","inscriptions":"\u00c9criture : \r ; hi\u00e9roglyphique","namesAndTitles":"Mout (Mout nebet...)","onomastics":"","dimension":[{"type":"Longueur","value":"1,16","displayDimension":"1,16 cm","unit":"cm","anteriorPrecision":"","posteriorPrecision":"","tri":2,"note":""},{"type":"Largeur","value":"0,81","displayDimension":"0,81 cm","unit":"cm","anteriorPrecision":"","posteriorPrecision":"","tri":3,"note":""},{"type":"Epaisseur","value":"0,37","displayDimension":"0,37 cm","unit":"cm","anteriorPrecision":"","posteriorPrecision":"","tri":5,"note":""}],"shape":"","materialsAndTechniques":"Mat\u00e9riau : pierre\r\nTechnique : gla\u00e7urage\r\nCouleur : vert","placeOfCreation":"","dateOfDiscovery":"","placeOfDiscovery":"","provenance":"","historicalContext":[],"objectHistory":"","jabachInventory":"","napoleonInventory":"","previousOwner":[],"acquisitionDetails":[{"mode":"ancien fonds","doubt":"","dates":[{"type":"date de l\u0027inscription sur l\u0027inventaire","value":"1989","startYear":1989,"endYear":1989}]}],"ownedBy":"Etat","heldBy":"Mus\u00e9e du Louvre, D\u00e9partement des Antiquit\u00e9s \u00e9gyptiennes","longTermLoanTo":"","index":{"Mode d\u0027acquisition":[{"value":"ancien fonds"}],"denomination":[{"value":"scarabo\u00efde"}],"material":[{"value":"pierre"}],"technic":[{"value":"gla\u00e7urage"}],"description":[{"value":"hi\u00e9roglyphes"},{"value":"mangeant"},{"value":"accroupi"},{"value":"singe"},{"value":"perc\u00e9 dans la longueur"}],"nameAndTitle":[{"value":"Mout"}],"period":[{"value":"Nouvel Empire"}],"inscriptionWritingSystem":[{"value":"hi\u00e9roglyphique"}]},"bibliography":[],"exhibition":[],"relatedWork":[],"image":[{"urlImage":"https:\/\/collections.louvre.fr\/media\/cache\/large\/0000000021\/0000027259\/0000584262_OG.JPG","urlThumbnail":"https:\/\/collections.louvre.fr\/media\/cache\/small\/0000000021\/0000027259\/0000584262_OG.JPG","copyright":"\u00a9 2015 Mus\u00e9e du Louvre \/ D\u00e9partement des Antiquit\u00e9s \u00e9gyptiennes","type":"vue d\u0027ensemble ; vue de dessus","position":0},{"urlImage":"https:\/\/collections.louvre.fr\/media\/cache\/large\/0000000021\/0000027259\/0000610197_OG.JPG","urlThumbnail":"https:\/\/collections.louvre.fr\/media\/cache\/small\/0000000021\/0000027259\/0000610197_OG.JPG","copyright":"\u00a9 2015 Mus\u00e9e du Louvre \/ D\u00e9partement des Antiquit\u00e9s \u00e9gyptiennes","type":"vue d\u0027ensemble ; vue de dessous","position":1}]}