{"arkId":"cl010331501","url":"https:\/\/collections.louvre.fr\/ark:\/53355\/cl010331501","modified ":"2025-10-31","title":"Fragment de tapis \u00e0 d\u00e9cor de m\u00e9daillons \u00e0 bords d\u00e9coup\u00e9s compris dans des rinceaux","titleComplement":"","denominationTitle":[{"type":"D\u00e9nomination","value":"Tapis"},{"type":"Titre","value":"Fragment de tapis \u00e0 d\u00e9cor de m\u00e9daillons \u00e0 bords d\u00e9coup\u00e9s compris dans des rinceaux"}],"displayDateCreated":"Date de cr\u00e9ation\/fabrication : XVIe si\u00e8cle ; XVIIe si\u00e8cle (1500 - 1700)","currentLocation":"non expos\u00e9","room":"","isMuseesNationauxRecuperation":false,"dateCreated":[{"startYear":1500,"endYear":1700,"imprecision":"","text":"XVIe si\u00e8cle ; XVIIe si\u00e8cle","type":"Date de cr\u00e9ation\/fabrication","doubt":""}],"creator":[],"objectNumber":[{"value":"AD 19542","type":"Num\u00e9ro principal"},{"value":"UCAD 19542","type":"Autre num\u00e9ro d\u0027inventaire"}],"collection":"D\u00e9partement des Arts de l\u0027Islam","printsDrawingsEntity":"","printsDrawingsCollection":"","objectType":"","originalObject":"","printState":"","description":"","inscriptions":"","namesAndTitles":"","onomastics":"","dimension":[{"type":"Largeur","value":"116","displayDimension":"116 cm","unit":"cm","anteriorPrecision":"","posteriorPrecision":"","tri":4,"note":""},{"type":"Longueur","value":"248","displayDimension":"248 cm","unit":"cm","anteriorPrecision":"","posteriorPrecision":"","tri":5,"note":""}],"shape":"","materialsAndTechniques":"Mat\u00e9riau : Textile\r\nMat\u00e9riau\/Technique : Poil : laine","placeOfCreation":"","dateOfDiscovery":"","placeOfDiscovery":"","provenance":"Iran (Monde iranien - Caucase) (Iran occidental (=nord-ouest))","historicalContext":[],"objectHistory":"","jabachInventory":"","napoleonInventory":"","previousOwner":[],"acquisitionDetails":[{"mode":"achat","doubt":"","dates":[{"type":"date","value":"11\/03\/1914","startYear":1914,"endYear":1914}]}],"ownedBy":"Etat","heldBy":"Union centrale des Arts D\u00e9coratifs, Paris","longTermLoanTo":"Mus\u00e9e du Louvre, AI, Paris","index":{"Mode d\u0027acquisition":[{"value":"achat"}],"place":[{"value":"Iran"}]},"bibliography":[{"bibliographyRef":"Alaoui, Brahim ; Passos Leite, Maria Fernanda (dir.), Le Ciel dans un tapis, cat. exp. (Paris, Institut du monde arabe, 2004\/2005. Lisbonne, Fondation Calouste Gulbenkian, 2005), Gand, Snoeck, 2004","bibliographyDate":"2004","bibliographyDetail":"p. 75, p. 152-153, p. 156-157, fig. 1, n\u00b034, n\u00b036","comparison":true}],"exhibition":[],"relatedWork":[],"image":[{"urlImage":"https:\/\/collections.louvre.fr\/media\/cache\/large\/0000000021\/0000331501\/0000663493_OG.JPG","urlThumbnail":"https:\/\/collections.louvre.fr\/media\/cache\/small\/0000000021\/0000331501\/0000663493_OG.JPG","copyright":"\u00a9 2005 Mus\u00e9e du Louvre, Dist. GrandPalaisRmn \/ Claire Tabbagh","type":"","position":0},{"urlImage":"https:\/\/collections.louvre.fr\/media\/cache\/large\/0000000021\/0000331501\/0000663494_OG.JPG","urlThumbnail":"https:\/\/collections.louvre.fr\/media\/cache\/small\/0000000021\/0000331501\/0000663494_OG.JPG","copyright":"\u00a9 2005 Mus\u00e9e du Louvre, Dist. GrandPalaisRmn \/ Claire Tabbagh","type":"","position":1}]}