{"arkId":"cl010221629","url":"https:\/\/collections.louvre.fr\/ark:\/53355\/cl010221629","modified ":"2025-08-19","title":"objet ind\u00e9termin\u00e9","titleComplement":"","denominationTitle":[{"type":"D\u00e9nomination","value":"objet ind\u00e9termin\u00e9"}],"displayDateCreated":"","currentLocation":"non expos\u00e9","room":"","isMuseesNationauxRecuperation":false,"dateCreated":[],"creator":[],"objectNumber":[{"value":"JC 117 030 6","type":"Num\u00e9ro principal"}],"collection":"Service de l\u0027Histoire du Louvre","printsDrawingsEntity":"","printsDrawingsCollection":"","objectType":"","originalObject":"","printState":"","description":"Monnaie rogn\u00e9e?\r\nSur l\u0027inventaire des arch\u00e9ologues : fragments, 2","inscriptions":"","namesAndTitles":"","onomastics":"","dimension":[{"type":"Longueur","value":"1,6","displayDimension":"1,6 cm","unit":"cm","anteriorPrecision":"","posteriorPrecision":"","tri":1,"note":""},{"type":"Largeur","value":"1,3","displayDimension":"1,3 cm","unit":"cm","anteriorPrecision":"","posteriorPrecision":"","tri":2,"note":""}],"shape":"","materialsAndTechniques":"Mat\u00e9riau : alliage cuivreux","placeOfCreation":"","dateOfDiscovery":"","placeOfDiscovery":"Jardins du Carrousel-\u003Ezone 117","provenance":"","historicalContext":[],"objectHistory":"","jabachInventory":"","napoleonInventory":"","previousOwner":[],"acquisitionDetails":[],"ownedBy":"Etat","heldBy":"Mus\u00e9e du Louvre, Service de l\u0027Histoire du Louvre","longTermLoanTo":"","index":{"denomination":[{"value":"objet ind\u00e9termin\u00e9"}],"material":[{"value":"alliage cuivreux"}],"place":[{"value":"zone 117"}]},"bibliography":[],"exhibition":[],"relatedWork":[],"image":[{"urlImage":"https:\/\/collections.louvre.fr\/media\/cache\/original\/0000000021\/0000221629\/0000359244_OG.JPG","urlThumbnail":"https:\/\/collections.louvre.fr\/media\/cache\/small\/0000000021\/0000221629\/0000359244_OG.JPG","copyright":"\u00a9 Mus\u00e9e du Louvre, Dist. GrandPalaisRmn \/ Pierre Philibert","type":"","position":0},{"urlImage":"https:\/\/collections.louvre.fr\/media\/cache\/original\/0000000021\/0000221629\/0000358931_OG.JPG","urlThumbnail":"https:\/\/collections.louvre.fr\/media\/cache\/small\/0000000021\/0000221629\/0000358931_OG.JPG","copyright":"\u00a9 Mus\u00e9e du Louvre, Dist. GrandPalaisRmn \/ Pierre Philibert","type":"","position":1}]}