{"arkId":"cl010033611","url":"https:\/\/collections.louvre.fr\/ark:\/53355\/cl010033611","modified ":"2025-09-02","title":"bague \u00e0 axe \u00e0 extr\u00e9mit\u00e9s enroul\u00e9es ; scarabo\u00efde","titleComplement":"","denominationTitle":[{"type":"D\u00e9nomination","value":"bague \u00e0 axe \u00e0 extr\u00e9mit\u00e9s enroul\u00e9es ; scarabo\u00efde"}],"displayDateCreated":"Date de cr\u00e9ation\/fabrication : Rams\u00e8s II (mention de personnage) (-1279 - -1213)","currentLocation":"non expos\u00e9","room":"","isMuseesNationauxRecuperation":false,"dateCreated":[{"startYear":-1279,"endYear":-1213,"imprecision":"","text":"Rams\u00e8s II","type":"Date de cr\u00e9ation\/fabrication","doubt":""}],"creator":[],"objectNumber":[{"value":"AF 6644","type":"Num\u00e9ro principal"}],"collection":"D\u00e9partement des Antiquit\u00e9s \u00e9gyptiennes","printsDrawingsEntity":"","printsDrawingsCollection":"","objectType":"","originalObject":"","printState":"","description":"D\u00e9cor : au recto ; sc\u00e8ne de guerre ; roi (debout, couronne bleue, pagne chendjit, tenant, cimeterre) ; prisonnier (\u00e0 genoux) \r\nau verso ; Amon (sphinx \u00e0 t\u00eate de b\u00e9lier, double plume droite) ; Ma\u00e2t ; serpent ail\u00e9","inscriptions":"\u00c9criture : \r ; hi\u00e9roglyphique\r ; Nature du texte : \r ; nom de couronnement","namesAndTitles":"Rams\u00e8s II","onomastics":"","dimension":[{"type":"Largeur","value":"2,38","displayDimension":"2,38 cm","unit":"cm","anteriorPrecision":"","posteriorPrecision":"","tri":3,"note":""},{"type":"Diam\u00e8tre","value":"1,95","displayDimension":"1,95 cm","unit":"cm","anteriorPrecision":"","posteriorPrecision":"","tri":4,"note":""}],"shape":"","materialsAndTechniques":"Mat\u00e9riau : bronze (?) (anneau), st\u00e9atite (?) (scaraboide)\r\nTechnique : gla\u00e7urage\r\nCouleur : vert bleu fonc\u00e9","placeOfCreation":"","dateOfDiscovery":"","placeOfDiscovery":"","provenance":"","historicalContext":[],"objectHistory":"","jabachInventory":"","napoleonInventory":"","previousOwner":[],"acquisitionDetails":[{"mode":"ancien fonds","doubt":"","dates":[{"type":"date de l\u0027inscription sur l\u0027inventaire","value":"1969","startYear":1969,"endYear":1969}]}],"ownedBy":"Etat","heldBy":"Mus\u00e9e du Louvre, D\u00e9partement des Antiquit\u00e9s \u00e9gyptiennes","longTermLoanTo":"","index":{"Mode d\u0027acquisition":[{"value":"ancien fonds"}],"denomination":[{"value":"scarabo\u00efde"},{"value":"bague \u00e0 axe \u00e0 extr\u00e9mit\u00e9s enroul\u00e9es"}],"material":[{"value":"bronze"},{"value":"st\u00e9atite"}],"technic":[{"value":"gla\u00e7urage"}],"description":[{"value":"cimeterre"},{"value":"tenant"},{"value":"au verso"},{"value":"au recto"},{"value":"roi"},{"value":"prisonnier"},{"value":"sc\u00e8ne de guerre"},{"value":"\u00e0 genoux"},{"value":"debout"},{"value":"double plume droite"},{"value":"couronne bleue"},{"value":"sphinx \u00e0 t\u00eate de b\u00e9lier"},{"value":"serpent ail\u00e9"},{"value":"Ma\u00e2t"},{"value":"Amon"},{"value":"pagne chendjit"}],"nameAndTitle":[{"value":"Rams\u00e8s II"}],"period":[{"value":"Rams\u00e8s II"}],"inscriptionType":[{"value":"nom de couronnement"}],"inscriptionWritingSystem":[{"value":"hi\u00e9roglyphique"}]},"bibliography":[{"bibliographyRef":"Heka. Magie et envo\u00fbtement dans l\u0027\u00c9gypte ancienne, cat. exp. (Paris, mus\u00e9e du Louvre 2000-2001), Paris, R\u00e9union des mus\u00e9es nationaux, 2000","bibliographyDate":"2000","bibliographyDetail":"p. 40 ; 105, n\u00b0 96","comparison":false},{"bibliographyRef":"Joannis, Claudette (dir.), Bijoux d\u0027hommes. Signes et insignes, cat. exp. (Argenton-eur-Creuse, Mus\u00e9e de la Chemiserie et de l\u0027\u00c9l\u00e9gance masculine, 12 juin-31 octobre 1999), Communaut\u00e9 des Communes d\u0027Argenton, Le P\u00eachereau, Saint-Marcel, 1999","bibliographyDate":"1999","bibliographyDetail":"p. 100, fig. 4 p. 30, n\u00b0 6","comparison":false}],"exhibition":[{"value":"Bijoux d\u0027hommes, signes et insignes, Carouge (Suisse), Mus\u00e9e de Carouge, 14\/03\/2001 - 27\/05\/2001 "},{"value":"Bijoux d\u0027hommes, signes et insignes, Mus\u00e9e de la chemiserie et de l\u0027\u00e9l\u00e9gance masculine, 12\/06\/1999 - 31\/10\/1999 "}],"relatedWork":[],"image":[{"urlImage":"https:\/\/collections.louvre.fr\/media\/cache\/large\/0000000021\/0000033611\/0000067294_OG.JPG","urlThumbnail":"https:\/\/collections.louvre.fr\/media\/cache\/small\/0000000021\/0000033611\/0000067294_OG.JPG","copyright":"\u00a9 2000 Mus\u00e9e du Louvre, Dist. GrandPalaisRmn \/ Georges Poncet","type":"","position":0},{"urlImage":"https:\/\/collections.louvre.fr\/media\/cache\/large\/0000000021\/0000033611\/0000149025_OG.JPG","urlThumbnail":"https:\/\/collections.louvre.fr\/media\/cache\/small\/0000000021\/0000033611\/0000149025_OG.JPG","copyright":"\u00a9 2012 Mus\u00e9e du Louvre \/ D\u00e9partement des Antiquit\u00e9s \u00e9gyptiennes","type":"","position":1},{"urlImage":"https:\/\/collections.louvre.fr\/media\/cache\/large\/0000000021\/0000033611\/0000067295_OG.JPG","urlThumbnail":"https:\/\/collections.louvre.fr\/media\/cache\/small\/0000000021\/0000033611\/0000067295_OG.JPG","copyright":"\u00a9 2000 Mus\u00e9e du Louvre, Dist. GrandPalaisRmn \/ Georges Poncet","type":"","position":2},{"urlImage":"https:\/\/collections.louvre.fr\/media\/cache\/large\/0000000021\/0000033611\/0000062739_OG.JPG","urlThumbnail":"https:\/\/collections.louvre.fr\/media\/cache\/small\/0000000021\/0000033611\/0000062739_OG.JPG","copyright":"\u00a9 1999 Mus\u00e9e du Louvre, Dist. GrandPalaisRmn \/ Georges Poncet","type":"","position":3}]}