{"arkId":"cl010483659","url":"https:\/\/collections.louvre.fr\/ark:\/53355\/cl010483659","modified ":"2025-08-25","title":"sifflet","titleComplement":"","denominationTitle":[{"type":"D\u00e9nomination","value":"sifflet"}],"displayDateCreated":"","currentLocation":"non expos\u00e9","room":"","isMuseesNationauxRecuperation":false,"dateCreated":[],"creator":[],"objectNumber":[{"value":"CN 13688","type":"Num\u00e9ro principal"},{"value":"3166","type":"Autre num\u00e9ro d\u0027inventaire"}],"collection":"Service de l\u0027Histoire du Louvre","printsDrawingsEntity":"","printsDrawingsCollection":"","objectType":"","originalObject":"","printState":"","description":"","inscriptions":"","namesAndTitles":"","onomastics":"","dimension":[{"type":"Epaisseur","value":"1,3","displayDimension":"1,3 cm","unit":"cm","anteriorPrecision":"","posteriorPrecision":"","tri":1,"note":""},{"type":"Longueur","value":"5,1","displayDimension":"5,1 cm","unit":"cm","anteriorPrecision":"","posteriorPrecision":"","tri":1,"note":""},{"type":"Largeur","value":"1,5","displayDimension":"1,5 cm","unit":"cm","anteriorPrecision":"","posteriorPrecision":"","tri":1,"note":""}],"shape":"","materialsAndTechniques":"Mat\u00e9riau : terre cuite","placeOfCreation":"","dateOfDiscovery":"","placeOfDiscovery":"Cour Napol\u00e9on-\u003Ezone 3 (US : 118)","provenance":"","historicalContext":[],"objectHistory":"","jabachInventory":"","napoleonInventory":"","previousOwner":[],"acquisitionDetails":[],"ownedBy":"Etat","heldBy":"Mus\u00e9e du Louvre, Service de l\u0027Histoire du Louvre","longTermLoanTo":"","index":{"denomination":[{"value":"sifflet"}],"material":[{"value":"terre cuite"}],"place":[{"value":"zone 3"}]},"bibliography":[],"exhibition":[],"relatedWork":[],"image":[{"urlImage":"https:\/\/collections.louvre.fr\/media\/cache\/large\/0000000021\/0000483659\/0001081530_OG.JPG","urlThumbnail":"https:\/\/collections.louvre.fr\/media\/cache\/small\/0000000021\/0000483659\/0001081530_OG.JPG","copyright":"\u00a9 2021 Mus\u00e9e du Louvre \/ Service Histoire du Louvre","type":"","position":0}]}