{"arkId":"cl010173787","url":"https:\/\/collections.louvre.fr\/ark:\/53355\/cl010173787","modified ":"2025-08-25","title":"perle ; pendentif","titleComplement":"","denominationTitle":[{"type":"D\u00e9nomination","value":"perle ; pendentif"}],"displayDateCreated":"","currentLocation":"non expos\u00e9","room":"","isMuseesNationauxRecuperation":false,"dateCreated":[],"creator":[],"objectNumber":[{"value":"N III 3414","type":"Num\u00e9ro principal"},{"value":"N III 875","type":"Autre num\u00e9ro d\u0027inventaire"},{"value":"Pottier 125","type":"Num\u00e9ro catalogue"}],"collection":"D\u00e9partement des Antiquit\u00e9s orientales","printsDrawingsEntity":"","printsDrawingsCollection":"","objectType":"","originalObject":"","printState":"","description":"Pr\u00e9cision sur l\u0027objet : Lot de 36 anneaux, un coquillage, un quadrilat\u00e8re et un fragment","inscriptions":"","namesAndTitles":"","onomastics":"","dimension":"","shape":"","materialsAndTechniques":"Mat\u00e9riau : coquillage = coquille, fa\u00efence, pierre, verre","placeOfCreation":"","dateOfDiscovery":"1852","placeOfDiscovery":"Tell Guirgor","provenance":"","historicalContext":[],"objectHistory":"","jabachInventory":"","napoleonInventory":"","previousOwner":[],"acquisitionDetails":[],"ownedBy":"Etat","heldBy":"Mus\u00e9e du Louvre, D\u00e9partement des Antiquit\u00e9s orientales","longTermLoanTo":"","index":{"denomination":[{"value":"perle"},{"value":"pendentif"}],"material":[{"value":"coquillage = coquille"},{"value":"fa\u00efence"},{"value":"verre"},{"value":"pierre"}],"place":[{"value":"Tell Guirgor"}]},"bibliography":[],"exhibition":[],"relatedWork":[],"image":[{"urlImage":"https:\/\/collections.louvre.fr\/media\/cache\/large\/0000000021\/0000173787\/0000870229_OG.JPG","urlThumbnail":"https:\/\/collections.louvre.fr\/media\/cache\/small\/0000000021\/0000173787\/0000870229_OG.JPG","copyright":"\u00a9 2018 Mus\u00e9e du Louvre \/ D\u00e9partement des Antiquit\u00e9s orientales","type":"","position":0},{"urlImage":"https:\/\/collections.louvre.fr\/media\/cache\/large\/0000000021\/0000173787\/0000605157_OG.JPG","urlThumbnail":"https:\/\/collections.louvre.fr\/media\/cache\/small\/0000000021\/0000173787\/0000605157_OG.JPG","copyright":"\u00a9 2014 Mus\u00e9e du Louvre \/ D\u00e9partement des Antiquit\u00e9s orientales","type":"","position":1}]}