{"arkId":"cl010422148","url":"https:\/\/collections.louvre.fr\/ark:\/53355\/cl010422148","modified ":"2025-11-18","title":"Moulage du tombeau de Youssef","titleComplement":"","denominationTitle":[{"type":"D\u00e9nomination","value":"Moulage (Reproduction moderne)"},{"type":"Titre","value":"Moulage du tombeau de Youssef"}],"displayDateCreated":"Date de cr\u00e9ation\/fabrication : XIe si\u00e8cle ; XIIe si\u00e8cle (1000 - 1200)","currentLocation":"non expos\u00e9","room":"","isMuseesNationauxRecuperation":false,"dateCreated":[{"startYear":1000,"endYear":1200,"imprecision":"","text":"XIe si\u00e8cle ; XIIe si\u00e8cle","type":"Date de cr\u00e9ation\/fabrication","doubt":""}],"creator":[],"objectNumber":[{"value":"AD PR 2011\/13 .1.1-4-2","type":"Num\u00e9ro principal"},{"value":"AD PR 2011\/13 .1.1-4","type":"Autre num\u00e9ro d\u0027inventaire"}],"collection":"D\u00e9partement des Arts de l\u0027Islam","printsDrawingsEntity":"","printsDrawingsCollection":"","objectType":"","originalObject":"","printState":"","description":"","inscriptions":"","namesAndTitles":"","onomastics":"","dimension":[{"type":"Epaisseur","value":"12","displayDimension":"12 cm","unit":"cm","anteriorPrecision":"","posteriorPrecision":"","tri":1,"note":""},{"type":"Hauteur","value":"126","displayDimension":"126 cm","unit":"cm","anteriorPrecision":"","posteriorPrecision":"","tri":1,"note":""},{"type":"Largeur","value":"137,5","displayDimension":"137,5 cm","unit":"cm","anteriorPrecision":"","posteriorPrecision":"","tri":1,"note":""}],"shape":"","materialsAndTechniques":"Mat\u00e9riau : Pl\u00e2tre\r\nMat\u00e9riau\/Technique : pl\u00e2tre","placeOfCreation":"","dateOfDiscovery":"","placeOfDiscovery":"","provenance":"Marrakech (Maghreb-\u003EMaroc)","historicalContext":[],"objectHistory":"","jabachInventory":"","napoleonInventory":"","previousOwner":[],"acquisitionDetails":[],"ownedBy":"Etat","heldBy":"Union centrale des Arts D\u00e9coratifs, Paris","longTermLoanTo":"Mus\u00e9e du Louvre, AI, Paris","index":{"place":[{"value":"Marrakech"}]},"bibliography":[],"exhibition":[],"relatedWork":[{"objectUrl":"https:\/\/collections.louvre.fr\/ark:\/53355\/cl010333265","type":"Ensemble"},{"objectUrl":"https:\/\/collections.louvre.fr\/ark:\/53355\/cl010422149","type":"Ensemble"},{"objectUrl":"https:\/\/collections.louvre.fr\/ark:\/53355\/cl010422151","type":"Ensemble"},{"objectUrl":"https:\/\/collections.louvre.fr\/ark:\/53355\/cl010422363","type":"Ensemble"}],"image":[{"urlImage":"https:\/\/collections.louvre.fr\/media\/cache\/large\/0000000021\/0000422148\/0000762973_OG.JPG","urlThumbnail":"https:\/\/collections.louvre.fr\/media\/cache\/small\/0000000021\/0000422148\/0000762973_OG.JPG","copyright":"\u00a9 2010 Mus\u00e9e du Louvre \/ D\u00e9partement des Arts de l\u0027Islam","type":"","position":0},{"urlImage":"https:\/\/collections.louvre.fr\/media\/cache\/large\/0000000021\/0000422148\/0000778743_OG.JPG","urlThumbnail":"https:\/\/collections.louvre.fr\/media\/cache\/small\/0000000021\/0000422148\/0000778743_OG.JPG","copyright":"\u00a9 2018 Mus\u00e9e du Louvre \/ D\u00e9partement des Arts de l\u0027Islam","type":"","position":1},{"urlImage":"https:\/\/collections.louvre.fr\/media\/cache\/large\/0000000021\/0000422148\/0000778755_OG.JPG","urlThumbnail":"https:\/\/collections.louvre.fr\/media\/cache\/small\/0000000021\/0000422148\/0000778755_OG.JPG","copyright":"\u00a9 2018 Mus\u00e9e du Louvre \/ D\u00e9partement des Arts de l\u0027Islam","type":"","position":2}]}