{"arkId":"cl020110446","url":"https:\/\/collections.louvre.fr\/ark:\/53355\/cl020110446","modified ":"2025-08-26","title":"\u0027La lutte pour l\u0027\u00e9tendard\u0027 de la \u0027Bataille d\u0027Anghiari\u0027","titleComplement":null,"denominationTitle":[{"type":"Titre","value":"\u0027La lutte pour l\u0027\u00e9tendard\u0027 de la \u0027Bataille d\u0027Anghiari\u0027"}],"displayDateCreated":"","currentLocation":"R\u00e9serve des tr\u00e8s grand format","room":"","isMuseesNationauxRecuperation":false,"dateCreated":[],"creator":[{"label":"Rubens, Petrus Paulus","attributionLevel":"attribution actuelle","linkType":"original","dates":[{"date":"1640","place":"Anvers","type":"date 2"},{"date":"1577","place":"Siegen (Westphalie)","type":"date 1"}],"creatorRole":"","authenticationType":"","doubt":"","attributedBy":"","attributedYear":"","wikidata":"Q5599"},{"label":"ANONYME ITALIEN XVI\u00e8 s","attributionLevel":"proposition d\u0027attribution","linkType":"original","creatorRole":"","authenticationType":"","doubt":"","attributedBy":"Logan, Anne-Marie","attributedYear":2003,"wikidata":""},{"label":"VINCI Leonardo da","linkType":"liaison avec un autre artiste","attributionLevel":"inspir\u00e9 par","date":[],"creatorRole":"","authenticationType":"","doubt":"","attributedBy":"","attributedYear":"","wikidata":""}],"objectNumber":[{"value":"INV 20271, Recto","type":"Num\u00e9ro principal"},{"value":"NIII 35368","type":"Anciens num\u00e9ros d\u0027inventaire"},{"value":"Flamands 1084","type":"Num\u00e9ros de catalogues"},{"value":"vol.8, p.330","type":"R\u00e9f\u00e9rence de l\u0027inventaire manuscrit"}],"collection":"D\u00e9partement des Arts graphiques","printsDrawingsEntity":"Cabinet des dessins","printsDrawingsCollection":"Fonds des dessins et miniatures","objectType":"","originalObject":"","printState":"","description":"","inscriptions":"","namesAndTitles":"","onomastics":"","dimension":[{"type":"Hauteur","value":"0.453","displayDimension":"0.453 m","unit":"m","anteriorPrecision":"\u00e0 la feuille","posteriorPrecision":"","tri":"","note":""},{"type":"Largeur","value":"0.636","displayDimension":"0.636 m","unit":"m","anteriorPrecision":"\u00e0 la feuille","posteriorPrecision":"","tri":"","note":""}],"shape":"","materialsAndTechniques":"Pierre noire, plume et encre brune, pinceau et encre brune et grise, lavis gris, rehauts de blanc et de gris-bleu, sur un feuillet agrandi par quatre bandes laterales (feuillet d\u0027origine : H. 0,428 m ; L. 0,577 m. Feuillet agrandi : H. 0,453 m. ; L. 0,636 m).","placeOfCreation":"","dateOfDiscovery":"","placeOfDiscovery":"","provenance":"","historicalContext":[],"objectHistory":"P. P. Rubens - E. Jabach, traces de l\u0027or du montage \u00e0 bande dor\u00e9e - Nicodemus Tessin - Carl Gustav Tessin - Nils Barck - acquis en 1852, marque du Louvre (L. 1886).","jabachInventory":"","napoleonInventory":"","previousOwner":[],"acquisitionDetails":[],"ownedBy":"","heldBy":"","longTermLoanTo":"","index":{"collection":[{"value":"Jabach, Everhard"},{"value":"Barck, Nils"},{"value":"Tessin, C. G., comte"},{"value":"Tessin, Nicodemus"},{"value":"Rubens, Pierre Paul"}],"place":[{"value":"Anghiari"},{"value":"Florence, Palazzo Vecchio, oeuvre en rapport"},{"value":"Italie+"}],"subject":[{"value":"Bataille d\u0027Anghiari, par Leonardo da Vinci"}],"technic":[{"value":"encre brune \u00e0 la plume"},{"value":"lavis (gris)"},{"value":"pierre noire"},{"value":"pinceau"},{"value":"rehauts de blanc"},{"value":"rehauts de gris-bleu"}]},"bibliography":[],"exhibition":[],"relatedWork":[],"image":[{"urlImage":"https:\/\/collections.louvre.fr\/media\/cache\/original\/11\/04\/46\/00\/AGO110446-000_PE.jpg","urlThumbnail":"https:\/\/collections.louvre.fr\/media\/cache\/small\/11\/04\/46\/00\/AGO110446-000_PE.jpg","copyright":"GrandPalaisRmn (Mus\u00e9e du Louvre) \/ Michel Urtado","type":"","position":0},{"urlImage":"https:\/\/collections.louvre.fr\/media\/cache\/original\/11\/04\/46\/00\/AGO110446-001_PE.jpg","urlThumbnail":"https:\/\/collections.louvre.fr\/media\/cache\/small\/11\/04\/46\/00\/AGO110446-001_PE.jpg","copyright":" GrandPalaisRmn","type":"Autre","position":1}]}