{"arkId":"cl020529306","url":"https:\/\/collections.louvre.fr\/ark:\/53355\/cl020529306","modified ":"2025-12-10","title":"La Valette (Jean Parisot de)","titleComplement":"Portrait de Jean Parisot de La Valette,  grand ma\u00eetre de l\u0027ordre de J\u00e9rusalem (1494-1568).","denominationTitle":[{"type":"Titre","value":"La Valette (Jean Parisot de)\/Portrait de Jean Parisot de La Valette,  grand ma\u00eetre de l\u0027ordre de J\u00e9rusalem (1494-1568)."}],"displayDateCreated":"","currentLocation":"Atelier de la chalcographie","room":"","isMuseesNationauxRecuperation":false,"dateCreated":[],"creator":[{"label":"GIRARDET Paul","attributionLevel":"attribution actuelle","linkType":"original","dates":[{"date":"1821","place":"","type":"date 1"},{"date":"1893","place":"","type":"date 2"}],"creatorRole":"","authenticationType":"","doubt":"","attributedBy":"","attributedYear":"","wikidata":"Q2059790"}],"objectNumber":[{"value":"566 FG\/ Recto","type":"Num\u00e9ro principal"},{"value":"G1506","type":"Anciens num\u00e9ros d\u0027inventaire"}],"collection":"D\u00e9partement des Arts graphiques","printsDrawingsEntity":"Chalcographie","printsDrawingsCollection":"","objectType":"","originalObject":"","printState":"","description":"","inscriptions":"","namesAndTitles":"","onomastics":"","dimension":[{"type":"Hauteur","value":"0.293","displayDimension":"0.293 m","unit":"m","anteriorPrecision":"\u00e0 la feuille","posteriorPrecision":"","tri":"","note":""},{"type":"Largeur","value":"0.241","displayDimension":"0.241 m","unit":"m","anteriorPrecision":"\u00e0 la feuille","posteriorPrecision":"","tri":"","note":""}],"shape":"","materialsAndTechniques":"Diagraphe et pantographe de Gavard.","placeOfCreation":"","dateOfDiscovery":"","placeOfDiscovery":"","provenance":"","historicalContext":[],"objectHistory":"","jabachInventory":"","napoleonInventory":"","previousOwner":[],"acquisitionDetails":[],"ownedBy":"","heldBy":"","longTermLoanTo":"","index":{"technic":[{"value":"eau-forte"},{"value":"burin"}]},"bibliography":[],"exhibition":[],"relatedWork":[],"image":[]}