{"arkId":"cl020007975","url":"https:\/\/collections.louvre.fr\/ark:\/53355\/cl020007975","modified ":"2025-08-19","title":"Le Christ entre les deux larrons","titleComplement":null,"denominationTitle":[{"type":"Titre","value":"Le Christ entre les deux larrons"}],"displayDateCreated":"","currentLocation":"Petit format","room":"","isMuseesNationauxRecuperation":false,"dateCreated":[],"creator":[{"label":"Marmitta, Francesco","attributionLevel":"attribution actuelle","linkType":"original","dates":[{"date":"apr\u00e8s 1505","place":"Parme ?","type":"date 2"},{"date":"vers 1460","place":"","type":"date 1"}],"creatorRole":"","authenticationType":"","doubt":"","attributedBy":"Longhi, Roberto","attributedYear":1934,"wikidata":"Q3027938"},{"label":"ANONYME VENITIEN fin XV\u00e8 s - d\u00e9but XVI\u00e8 s","attributionLevel":"ancienne attribution","linkType":"original","creatorRole":"","authenticationType":"","doubt":"","attributedBy":"","attributedYear":"","wikidata":""}],"objectNumber":[{"value":"INV 5609, Recto","type":"Num\u00e9ro principal"},{"value":"NIII 20","type":"Anciens num\u00e9ros d\u0027inventaire"},{"value":"vol.3, p.157","type":"R\u00e9f\u00e9rence de l\u0027inventaire manuscrit"}],"collection":"D\u00e9partement des Arts graphiques","printsDrawingsEntity":"Cabinet des dessins","printsDrawingsCollection":"Fonds des dessins et miniatures","objectType":"","originalObject":"","printState":"","description":"","inscriptions":"","namesAndTitles":"","onomastics":"","dimension":[{"type":"Hauteur","value":"0.31","displayDimension":"0.31 m","unit":"m","anteriorPrecision":"\u00e0 la feuille","posteriorPrecision":"","tri":"","note":""},{"type":"Largeur","value":"0.2","displayDimension":"0.2 m","unit":"m","anteriorPrecision":"\u00e0 la feuille","posteriorPrecision":"","tri":"","note":""}],"shape":"","materialsAndTechniques":"encre brune \u00e0 la plume;lavis (brun);v\u00e9lin;aquarelle;encre de couleur \u00e0 la plume","placeOfCreation":"","dateOfDiscovery":"","placeOfDiscovery":"","provenance":"","historicalContext":[],"objectHistory":"E. Jabach (L. 2959) ; montage \u00e0 bande dor\u00e9e des dessins d\u0027ordonnance ; Inventaire Jabach, I, n\u00b0 4 (Andrea Orcagna) - Entr\u00e9 dans le Cabinet du Roi en 1671 ; paraphe de J. Prioult (L. 2953).Notice de l\u0027inventaire Jabach :Dessin dit d\u0027ordonnance coll\u00e9 et dor\u00e9 de la collection d\u0027Everhard Jabach,\nacquis pour le roi en 1671\n\nA. Crit\u00e8res de l\u0027identification\n\nLe dessin a conserv\u00e9 tous les signes attestant sa provenance et son acquisition en 1671 :\n\n- montage Jabach ivoire \u00e0 large bande d\u0027or fin ;\n- num\u00e9ro d\u0027inventaire Jabach \u00e0 la sanguine, au verso du montage ;\n- paraphe Jabach \u00e0 l\u0027encre brune [L. 2959], au verso du montage ;\n\n- marques, au verso du montage, du r\u00e9colement du fonds Jabach effectu\u00e9 en 1690 par Jean Prioult, commissaire-enqu\u00eateur au Ch\u00e2telet de Paris, \u00e0 la suite du d\u00e9c\u00e8s de Charles Le Brun, premier peintre du roi, directeur et garde g\u00e9n\u00e9ral du Cabinet des tableaux et dessins :\n\n- transcription en toutes lettres du num\u00e9ro d\u0027inventaire Jabach ;\n- paraphe Prioult [L. 2953].\n\nL\u0027iconographie, la technique et les dimensions du montage sont en accord avec la description donn\u00e9e par la notice de l\u0027inventaire Jabach correspondant au num\u00e9ro d\u0027inventaire \u00e0 la sanguine.\n\nB. Notice de l\u0027Inventaire Jabach, f\u00e9vrier 1671. Minute.\nParis, Archives nationales, O1 1967.\n\nInvantaire de 517 desseins d\u0027ordonnances escole florentinne :\n\n4\n\nNostre Seigneur crucefi\u00e9 entre les deux laron ou il y a quantit\u00e9 de figure entiere a la plume et lav\u00e9 sur de papier rous de 10 pouce de long sur 14 1\/2 pouce de haut\n\nde Andrea Orgagna [Orcagna]Inventaire du mus\u00e9e Napol\u00e9on :Inventaire du Mus\u00e9e Napol\u00e9on. Dessins. Vol.1, p.4, chap. : Ecole florentine, carton 1. (...) Num\u00e9ro : 21. Nom du ma\u00eetre : Masaccio. Num\u00e9ro d\u0027ordre dans l\u0027oeuvre du ma\u00eetre : 9. D\u00e9signation des sujets : Le Christ en croix entre les deux larrons. Dessin \u00e0 la plume, et lav\u00e9 au bistre sur V\u00e9lin  Expos\u00e9 depuis l\u0027an dix dans la Galerie d\u0027Apollon, et port\u00e9 dans la notice de l\u0027an douze, sous le n\u00b0 181 et dans celle de 1811, sous le n\u00b0 213.  La derni\u00e8re phrase barr\u00e9e#227 au crayon Dimensions : H. 31 x L. 20cm. Origine : Collection ancienne.Prix de l\u0027estimation de l\u0027objet : 500francs. Emplacement actuel : Galerie d\u0027Apollon. Observations : Il y est encore au crayon. Signe de recollement : Vu au crayon#trait oblique \/ au crayon \/ sur le n\u00b0 d\u0027ordre#trait oblique \/ au crayon \/ sous le n\u00b0 Morel d\u0027Arleux. Cote : 1DD33","jabachInventory":"Dessin dit d\u0027ordonnance coll\u00e9 et dor\u00e9 de la collection d\u0027Everhard Jabach,\nacquis pour le roi en 1671\n\nA. Crit\u00e8res de l\u0027identification\n\nLe dessin a conserv\u00e9 tous les signes attestant sa provenance et son acquisition en 1671 :\n\n- montage Jabach ivoire \u00e0 large bande d\u0027or fin ;\n- num\u00e9ro d\u0027inventaire Jabach \u00e0 la sanguine, au verso du montage ;\n- paraphe Jabach \u00e0 l\u0027encre brune [L. 2959], au verso du montage ;\n\n- marques, au verso du montage, du r\u00e9colement du fonds Jabach effectu\u00e9 en 1690 par Jean Prioult, commissaire-enqu\u00eateur au Ch\u00e2telet de Paris, \u00e0 la suite du d\u00e9c\u00e8s de Charles Le Brun, premier peintre du roi, directeur et garde g\u00e9n\u00e9ral du Cabinet des tableaux et dessins :\n\n- transcription en toutes lettres du num\u00e9ro d\u0027inventaire Jabach ;\n- paraphe Prioult [L. 2953].\n\nL\u0027iconographie, la technique et les dimensions du montage sont en accord avec la description donn\u00e9e par la notice de l\u0027inventaire Jabach correspondant au num\u00e9ro d\u0027inventaire \u00e0 la sanguine.\n\nB. Notice de l\u0027Inventaire Jabach, f\u00e9vrier 1671. Minute.\nParis, Archives nationales, O1 1967.\n\nInvantaire de 517 desseins d\u0027ordonnances escole florentinne :\n\n4\n\nNostre Seigneur crucefi\u00e9 entre les deux laron ou il y a quantit\u00e9 de figure entiere a la plume et lav\u00e9 sur de papier rous de 10 pouce de long sur 14 1\/2 pouce de haut\n\nde Andrea Orgagna [Orcagna]","napoleonInventory":"Inventaire du Mus\u00e9e Napol\u00e9on. Dessins. Vol.1, p.4, chap. : Ecole florentine, carton 1. (...) Num\u00e9ro : 21. Nom du ma\u00eetre : Masaccio. Num\u00e9ro d\u0027ordre dans l\u0027oeuvre du ma\u00eetre : 9. D\u00e9signation des sujets : Le Christ en croix entre les deux larrons. Dessin \u00e0 la plume, et lav\u00e9 au bistre sur V\u00e9lin  Expos\u00e9 depuis l\u0027an dix dans la Galerie d\u0027Apollon, et port\u00e9 dans la notice de l\u0027an douze, sous le n\u00b0 181 et dans celle de 1811, sous le n\u00b0 213.  La derni\u00e8re phrase barr\u00e9e#227 au crayon Dimensions : H. 31 x L. 20cm. Origine : Collection ancienne.Prix de l\u0027estimation de l\u0027objet : 500francs. Emplacement actuel : Galerie d\u0027Apollon. Observations : Il y est encore au crayon. Signe de recollement : Vu au crayon#trait oblique \/ au crayon \/ sur le n\u00b0 d\u0027ordre#trait oblique \/ au crayon \/ sous le n\u00b0 Morel d\u0027Arleux. Cote : 1DD33","previousOwner":[{"value":"Derni\u00e8re provenance : Jabach, Everhard","note":""}],"acquisitionDetails":[],"ownedBy":"","heldBy":"","longTermLoanTo":"","index":{"place":[{"value":"Londres, British Museum, oeuvre en rapport"}],"person":[{"value":"Marie Madeleine, sainte"},{"value":"J\u00e9sus-Christ"},{"value":"Vierge Marie"},{"value":"Jean l\u0027Evang\u00e9liste, saint"},{"value":"Sainte Femme"}],"subject":[{"value":"ICONOGRAPHIE RELIGIEUSE"},{"value":"Crucifixion"},{"value":"Christ et les deux larrons"}],"technic":[{"value":"encre brune \u00e0 la plume"},{"value":"lavis (brun)"},{"value":"v\u00e9lin"},{"value":"aquarelle"},{"value":"encre de couleur \u00e0 la plume"}]},"bibliography":[],"exhibition":[],"relatedWork":[],"image":[{"urlImage":"https:\/\/collections.louvre.fr\/media\/cache\/original\/00\/79\/75\/00\/AGO007975-000_PE.jpg","urlThumbnail":"https:\/\/collections.louvre.fr\/media\/cache\/small\/00\/79\/75\/00\/AGO007975-000_PE.jpg","copyright":" GrandPalaisRmn","type":"","position":0}]}