{"arkId":"cl020503963","url":"https:\/\/collections.louvre.fr\/ark:\/53355\/cl020503963","modified ":"2025-08-25","title":"Les Noces d\u0027Alexandre et Roxane","titleComplement":null,"denominationTitle":[{"type":"Titre","value":"Les Noces d\u0027Alexandre et Roxane"}],"displayDateCreated":"","currentLocation":"restitu\u00e9 \u00e0 son propri\u00e9taire","room":"","isMuseesNationauxRecuperation":true,"dateCreated":[],"creator":[{"label":"Parmesan (Francesco Mazzola, dit Il Parmigianino, ou Le)","attributionLevel":"attribution actuelle","linkType":"attribu\u00e9 \u00e0","dates":[{"date":"1540","place":"Casalmaggiore (Cr\u00e9mone)","type":"date 2"},{"date":"1503","place":"Parme","type":"date 1"}],"creatorRole":"","authenticationType":"","doubt":"","attributedBy":"","attributedYear":"","wikidata":"Q9348"}],"objectNumber":[{"value":"REC 68, Recto","type":"Num\u00e9ro principal"}],"collection":"D\u00e9partement des Arts graphiques","printsDrawingsEntity":"Cabinet des dessins","printsDrawingsCollection":"Fonds des dessins provenant de la Commission de r\u00e9cup\u00e9ration","objectType":"","originalObject":"","printState":"","description":"","inscriptions":"","namesAndTitles":"","onomastics":"","dimension":[{"type":"Hauteur","value":"0.146","displayDimension":"0.146 m","unit":"m","anteriorPrecision":"\u00e0 la feuille","posteriorPrecision":"","tri":"","note":""},{"type":"Largeur","value":"0.222","displayDimension":"0.222 m","unit":"m","anteriorPrecision":"\u00e0 la feuille","posteriorPrecision":"","tri":"","note":""}],"shape":"","materialsAndTechniques":"Plume et encre brune, lavis brun. Annotations manuscrites au verso.","placeOfCreation":"","dateOfDiscovery":"","placeOfDiscovery":"","provenance":"","historicalContext":[],"objectHistory":"Collection Earl of Arundel (?), selon l\u0027annotation au verso du montage : \u0027Vi \u00e9 la stampa intagliata all\u0027 acqua forte in Londra da Enrico van der Borcht d\u00e0 questo \/ disegno, ch\u0027era [...] quelli dello studio famoso del [...] Conte d\u0027Arondell Inglese\u0027 - Seconde collection de Everhard Jabach (L. 2959) ; montage \u00e0 bande dor\u00e9e des dessins d\u0027ordonnance ; indication de format Q\u00b0 (L. 2960) - Collection Dominique-Vivant Denon, marque en bas \u00e0 droite (Lugt 779) ; sa vente, 1826, n\u00b0 388, achet\u00e9 235 livres par Antoine-Jean  Baron Gros - Collection Comte Nils Barck, marque en bas \u00e0 gauche (Lugt 1959) - Anatole France, vente Paris, H\u00f4tel Drouot, salle 6, 20-21 avril 1932, n\u00b0 122 -  M. Gentili di Giuseppe, vente Paris, H\u00f4tel Drouot, 23 avril 1941, lot 19 - vente Paris, H\u00f4tel Drouot, salle 6, 15 d\u00e9cembre 1941, lot 22 - Au verso du montage, cachet du Staedtkunstsammlungen, D\u00fcsseldorf, (n\u00b042-1) - Remis au Cabinet des Dessins par la Commission de r\u00e9cup\u00e9ration artistique le 23 d\u00e9cembre 1949. Pour consulter la base des MNR (Mus\u00e9es nationaux R\u00e9cup\u00e9ration), adresse du site Rose-Valland : www.culture.gouv.fr\/public\/mistral\/mnrbis_fr\nRestitu\u00e9 aux ayants-droit le 13 mars 2017.","jabachInventory":"","napoleonInventory":"","previousOwner":[],"acquisitionDetails":[],"ownedBy":"","heldBy":"","longTermLoanTo":"","index":{"collection":[{"value":"Jabach, Everhard"},{"value":"Barck, Nils"},{"value":"Howard, Thomas, Comte d\u0027Arundel"},{"value":"Denon, Dominique Vivant, baron"},{"value":"Gros, Antoine-Jean"}],"place":[{"value":"Vienne, Albertina, Graphische Sammlung, oeuvre en rapport"},{"value":"Florence, Galleria degli Uffizi, oeuvre en rapport"}],"person":[{"value":"Alexandre"},{"value":"Roxane"}],"subject":[{"value":"Noces d\u0027Alexandre et Roxane"}],"technic":[{"value":"encre brune \u00e0 la plume"},{"value":"lavis (brun)"}]},"bibliography":[],"exhibition":[],"relatedWork":[],"image":[{"urlImage":"https:\/\/collections.louvre.fr\/media\/cache\/original\/50\/39\/63\/00\/AGO503963-000_PE.jpg","urlThumbnail":"https:\/\/collections.louvre.fr\/media\/cache\/small\/50\/39\/63\/00\/AGO503963-000_PE.jpg","copyright":"GrandPalaisRmn (Mus\u00e9e du Louvre) \/ Michel Urtado","type":"","position":0},{"urlImage":"https:\/\/collections.louvre.fr\/media\/cache\/original\/50\/39\/63\/00\/AGO503963-001_PE.jpg","urlThumbnail":"https:\/\/collections.louvre.fr\/media\/cache\/small\/50\/39\/63\/00\/AGO503963-001_PE.jpg","copyright":" GrandPalaisRmn","type":"Environnement","position":1},{"urlImage":"https:\/\/collections.louvre.fr\/media\/cache\/original\/50\/39\/63\/00\/AGO503963-002_PE.jpg","urlThumbnail":"https:\/\/collections.louvre.fr\/media\/cache\/small\/50\/39\/63\/00\/AGO503963-002_PE.jpg","copyright":"GrandPalaisRmn (Mus\u00e9e du Louvre) \/ Michel Urtado","type":"D\u00e9tail","position":2}]}