{"arkId":"cl020215972","url":"https:\/\/collections.louvre.fr\/ark:\/53355\/cl020215972","modified ":"2025-08-20","title":"Haute p\u00e2ture en Auvergne","titleComplement":null,"denominationTitle":[{"type":"Titre","value":"Haute p\u00e2ture en Auvergne"}],"displayDateCreated":"","currentLocation":"Petit format","room":"","isMuseesNationauxRecuperation":false,"dateCreated":[],"creator":[{"label":"Millet, Jean Francois","attributionLevel":"attribution actuelle","linkType":"original","dates":[{"date":"1814","place":"","type":"date 1"},{"date":"1875","place":"","type":"date 2"}],"creatorRole":"","authenticationType":"","doubt":"","attributedBy":"","attributedYear":"","wikidata":"Q148458"}],"objectNumber":[{"value":"RF 5870, Recto","type":"Num\u00e9ro principal"},{"value":"Guiffrey et Marcel 10530","type":"Num\u00e9ros de catalogues"},{"value":"vol.21, p.141","type":"R\u00e9f\u00e9rence de l\u0027inventaire manuscrit"}],"collection":"D\u00e9partement des Arts graphiques","printsDrawingsEntity":"Cabinet des dessins","printsDrawingsCollection":"Fonds des dessins et miniatures, collection du mus\u00e9e d\u0027Orsay","objectType":"","originalObject":"","printState":"","description":"","inscriptions":"","namesAndTitles":"","onomastics":"","dimension":[{"type":"Hauteur","value":"0.207","displayDimension":"0.207 m","unit":"m","anteriorPrecision":"\u00e0 la feuille","posteriorPrecision":"","tri":"","note":""},{"type":"Largeur","value":"0.28","displayDimension":"0.28 m","unit":"m","anteriorPrecision":"\u00e0 la feuille","posteriorPrecision":"","tri":"","note":""}],"shape":"","materialsAndTechniques":"Inscription en bas : \u0027Sur la hauteur parc \u00e0 vaches, gen\u00eats et branches mises debout pour faire abri aux vaches\u0027.","placeOfCreation":"","dateOfDiscovery":"","placeOfDiscovery":"","provenance":"","historicalContext":[],"objectHistory":"Ce dessin \u00e9tait autrefois rapport\u00e9 au recto du folio 52 de l\u0027album 2 de Millet.","jabachInventory":"","napoleonInventory":"","previousOwner":[{"value":"Derni\u00e8re provenance : Bonnat, L\u00e9on","note":""}],"acquisitionDetails":[{"mode":"legs","doubt":"","dates":[{"startYear":1922,"endYear":null}]}],"ownedBy":"","heldBy":"","longTermLoanTo":"","index":{"collection":[{"value":"Bonnat, L\u00e9on"}],"place":[{"value":"Auvergne"}],"technic":[{"value":"crayon (noir)"},{"value":"encre brune \u00e0 la plume"}]},"bibliography":[],"exhibition":[],"relatedWork":[],"image":[{"urlImage":"https:\/\/collections.louvre.fr\/media\/cache\/original\/21\/59\/72\/00\/AGO215972-000_PE.jpg","urlThumbnail":"https:\/\/collections.louvre.fr\/media\/cache\/small\/21\/59\/72\/00\/AGO215972-000_PE.jpg","copyright":"GrandPalaisRmn \/ Thierry Le Mage","type":"","position":0},{"urlImage":"https:\/\/collections.louvre.fr\/media\/cache\/original\/21\/59\/72\/00\/AGO215972-001_PE.jpg","urlThumbnail":"https:\/\/collections.louvre.fr\/media\/cache\/small\/21\/59\/72\/00\/AGO215972-001_PE.jpg","copyright":" GrandPalaisRmn","type":"Autre","position":1}]}