{"arkId":"cl020016644","url":"https:\/\/collections.louvre.fr\/ark:\/53355\/cl020016644","modified ":"2025-08-19","title":"Ch\u00e2teau de Versailles. Vue prise de la pi\u00e8ce d\u0027eau des Suisses","titleComplement":null,"denominationTitle":[{"type":"Titre","value":"Ch\u00e2teau de Versailles. Vue prise de la pi\u00e8ce d\u0027eau des Suisses"}],"displayDateCreated":"1848","currentLocation":"Mus\u00e9e d\u0027Orsay","room":"","isMuseesNationauxRecuperation":false,"dateCreated":[{"startYear":1848,"endYear":"","text":null,"type":"Date de cr\u00e9ation\/fabrication","doubt":""}],"creator":[{"label":"MAGNE Auguste Joseph","attributionLevel":"attribution actuelle","linkType":"original","dates":[{"date":"1816","place":"","type":"date 1"},{"date":"1885","place":"","type":"date 2"}],"creatorRole":"","authenticationType":"","doubt":"","attributedBy":"","attributedYear":"","wikidata":"Q2871000"}],"objectNumber":[{"value":"RF 4003, Recto","type":"Num\u00e9ro principal"},{"value":"vol.20, p.160","type":"R\u00e9f\u00e9rence de l\u0027inventaire manuscrit"}],"collection":"D\u00e9partement des Arts graphiques","printsDrawingsEntity":"Cabinet des dessins","printsDrawingsCollection":"Fonds des dessins et miniatures, collection du mus\u00e9e d\u0027Orsay","objectType":"","originalObject":"","printState":"","description":"","inscriptions":"","namesAndTitles":"","onomastics":"","dimension":[{"type":"Hauteur","value":"0.282","displayDimension":"0.282 m","unit":"m","anteriorPrecision":"\u00e0 la feuille","posteriorPrecision":"","tri":"","note":""},{"type":"Largeur","value":"0.383","displayDimension":"0.383 m","unit":"m","anteriorPrecision":"\u00e0 la feuille","posteriorPrecision":"","tri":"","note":""}],"shape":"","materialsAndTechniques":"encre noire \u00e0 la plume","placeOfCreation":"","dateOfDiscovery":"","placeOfDiscovery":"","provenance":"","historicalContext":[],"objectHistory":"","jabachInventory":"","napoleonInventory":"","previousOwner":[],"acquisitionDetails":[],"ownedBy":"","heldBy":"","longTermLoanTo":"","index":{"place":[{"value":"Versailles, ch\u00e2teau"}],"technic":[{"value":"encre noire \u00e0 la plume"}]},"bibliography":[],"exhibition":[],"relatedWork":[],"image":[]}