{"arkId":"cl020515846","url":"https:\/\/collections.louvre.fr\/ark:\/53355\/cl020515846","modified ":"2025-08-20","title":"Vue de la ville de Nuremberg prise \u00e0 l\u0027est","titleComplement":null,"denominationTitle":[{"type":"Titre","value":"Vue de la ville de Nuremberg prise \u00e0 l\u0027est"}],"displayDateCreated":"","currentLocation":"R\u00e9serve Edmond de Rothschild, grand format","room":"","isMuseesNationauxRecuperation":false,"dateCreated":[],"creator":[{"label":"LAUTENSACK Hanns","attributionLevel":"attribution actuelle","linkType":"original","dates":[{"date":"Vers 1520","place":"","type":"date 1"},{"date":"Vers 1564\/1566","place":"","type":"date 2"}],"creatorRole":"","authenticationType":"","doubt":"","attributedBy":"","attributedYear":"","wikidata":"Q1392217"}],"objectNumber":[{"value":"800 LR\/ Recto","type":"Num\u00e9ro principal"},{"value":"16284","type":"Anciens num\u00e9ros d\u0027inventaire"},{"value":"vol.1, p.42","type":"R\u00e9f\u00e9rence de l\u0027inventaire manuscrit"}],"collection":"D\u00e9partement des Arts graphiques","printsDrawingsEntity":"Collection Edmond de Rothschild","printsDrawingsCollection":"","objectType":"","originalObject":"","printState":"","description":"","inscriptions":"","namesAndTitles":"","onomastics":"","dimension":[{"type":"Hauteur","value":"0.31","displayDimension":"0.31 m","unit":"m","anteriorPrecision":"\u00e0 la feuille","posteriorPrecision":"","tri":"","note":""},{"type":"Largeur","value":"0.497","displayDimension":"0.497 m","unit":"m","anteriorPrecision":"\u00e0 la feuille","posteriorPrecision":"","tri":"","note":""}],"shape":"","materialsAndTechniques":"","placeOfCreation":"","dateOfDiscovery":"","placeOfDiscovery":"","provenance":"","historicalContext":[],"objectHistory":"\u0152uvre conserv\u00e9e dans le portefeuille n\u00b050 du baron Edmond de Rothschild jusqu\u0027en 2016.","jabachInventory":"","napoleonInventory":"","previousOwner":[{"value":"Derni\u00e8re provenance : Rothschild, baron Edmond de","note":""}],"acquisitionDetails":[{"mode":"don","doubt":"","dates":[{"startYear":1935,"endYear":null}]}],"ownedBy":"","heldBy":"","longTermLoanTo":"","index":{"place":[{"value":"Nuremberg"}]},"bibliography":[],"exhibition":[],"relatedWork":[],"image":[{"urlImage":"https:\/\/collections.louvre.fr\/media\/cache\/original\/51\/58\/46\/00\/AGO515846-001_PE.jpg","urlThumbnail":"https:\/\/collections.louvre.fr\/media\/cache\/small\/51\/58\/46\/00\/AGO515846-001_PE.jpg","copyright":"Mus\u00e9e du Louvre - D\u00e9partement des Arts Graphiques","type":"D\u00e9tail","position":1},{"urlImage":"https:\/\/collections.louvre.fr\/media\/cache\/original\/51\/58\/46\/00\/AGO515846-002_PE.jpg","urlThumbnail":"https:\/\/collections.louvre.fr\/media\/cache\/small\/51\/58\/46\/00\/AGO515846-002_PE.jpg","copyright":"Mus\u00e9e du Louvre - D\u00e9partement des Arts Graphiques","type":"Environnement","position":2}]}